zsfile.py
zsfile-0.1.0.dist-info/LICENSE
zsfile-0.1.0.dist-info/METADATA
zsfile-0.1.0.dist-info/WHEEL
zsfile-0.1.0.dist-info/entry_points.txt
zsfile-0.1.0.dist-info/top_level.txt
zsfile-0.1.0.dist-info/RECORD
