Metadata-Version: 2.1
Name: zsfile
Version: 0.1.0
Summary: zstandard compress and decompress tool.
Author: zencore
Author-email: dobetter@zencore.cn
License: MIT
Keywords: zsfile,zstandard
Classifier: Development Status :: 5 - Production/Stable
Classifier: Intended Audience :: Developers
Classifier: Topic :: Software Development :: Libraries :: Python Modules
Classifier: License :: OSI Approved :: MIT License
Classifier: Programming Language :: Python :: 3
Classifier: Programming Language :: Python :: 3 :: Only
License-File: LICENSE
Requires-Dist: click
Requires-Dist: zstandard
